thedebugger/__init__.py
thedebugger/llms.py
thedebugger/tools.py
thedebugger-0.2.1.dist-info/LICENSE
thedebugger-0.2.1.dist-info/METADATA
thedebugger-0.2.1.dist-info/WHEEL
thedebugger-0.2.1.dist-info/top_level.txt
thedebugger-0.2.1.dist-info/RECORD
