Metadata-Version: 2.1
Name: thedebugger
Version: 0.2.1
Summary: Uma biblioteca para depuração usando modelos de linguagem
Home-page: https://github.com/SaideOmaer1240/TheDebugger
Author: Saide Omar Saide
Author-email: saideomarsaid@gmail.com
Classifier: Programming Language :: Python :: 3
Classifier: License :: OSI Approved :: MIT License
Classifier: Operating System :: OS Independent
Requires-Python: >=3.7
License-File: LICENSE
Requires-Dist: google-generativeai
Requires-Dist: Pillow
Requires-Dist: langchain-core
Requires-Dist: langchain-groq
Requires-Dist: openai
Requires-Dist: colorama
